<annotation>
	<folder>image</folder>
	<filename>174.jpg</filename>
	<path>/home/ostap/Documents/project/ImageWork/Beta1/beerBottle/battle/image/174.jpg</path>
	<source>
		<database>Unknown</database>
	</source>
	<size>
		<width>900</width>
		<height>1200</height>
		<depth>3</depth>
	</size>
	<segmented>0</segmented>
	<object>
		<name>beerBottle</name>
		<pose>Unspecified</pose>
		<truncated>0</truncated>
		<difficult>0</difficult>
		<bndbox>
			<xmin>180</xmin>
			<ymin>481</ymin>
			<xmax>309</xmax>
			<ymax>962</ymax>
		</bndbox>
	</object>
</annotation>
