<annotation>
	<folder>image</folder>
	<filename>69.jpg</filename>
	<path>/home/ostap/Documents/project/ImageWork/Beta1/beerBottle/battle/image/69.jpg</path>
	<source>
		<database>Unknown</database>
	</source>
	<size>
		<width>1080</width>
		<height>1080</height>
		<depth>3</depth>
	</size>
	<segmented>0</segmented>
	<object>
		<name>beerBottle</name>
		<pose>Unspecified</pose>
		<truncated>1</truncated>
		<difficult>0</difficult>
		<bndbox>
			<xmin>599</xmin>
			<ymin>31</ymin>
			<xmax>915</xmax>
			<ymax>1080</ymax>
		</bndbox>
	</object>
</annotation>
